lightautoml_gpu/__init__.py
lightautoml_gpu/addons/__init__.py
lightautoml_gpu/addons/autots/base.py
lightautoml_gpu/addons/interpretation/__init__.py
lightautoml_gpu/addons/interpretation/data_process.py
lightautoml_gpu/addons/interpretation/l2x.py
lightautoml_gpu/addons/interpretation/l2x_model.py
lightautoml_gpu/addons/interpretation/lime.py
lightautoml_gpu/addons/interpretation/utils.py
lightautoml_gpu/addons/uplift/__init__.py
lightautoml_gpu/addons/uplift/base.py
lightautoml_gpu/addons/uplift/metalearners.py
lightautoml_gpu/addons/uplift/metrics.py
lightautoml_gpu/addons/uplift/utils.py
lightautoml_gpu/addons/utilization/__init__.py
lightautoml_gpu/addons/utilization/utilization.py
lightautoml_gpu/automl/__init__.py
lightautoml_gpu/automl/base.py
lightautoml_gpu/automl/blend.py
lightautoml_gpu/automl/gpu/__init__.py
lightautoml_gpu/automl/gpu/blend_gpu.py
lightautoml_gpu/automl/presets/__init__.py
lightautoml_gpu/automl/presets/base.py
lightautoml_gpu/automl/presets/gpu/__init__.py
lightautoml_gpu/automl/presets/gpu/tabular_configs_gpu/conf_0_sel_type_0.yml
lightautoml_gpu/automl/presets/gpu/tabular_configs_gpu/conf_1_sel_type_1.yml
lightautoml_gpu/automl/presets/gpu/tabular_configs_gpu/conf_2_select_mode_1_no_typ.yml
lightautoml_gpu/automl/presets/gpu/tabular_configs_gpu/conf_3_sel_type_1_no_inter_lgbm.yml
lightautoml_gpu/automl/presets/gpu/tabular_configs_gpu/conf_4_sel_type_0_no_int.yml
lightautoml_gpu/automl/presets/gpu/tabular_configs_gpu/conf_5_sel_type_1_tuning_full.yml
lightautoml_gpu/automl/presets/gpu/tabular_configs_gpu/conf_6_sel_type_1_tuning_full_no_int_lgbm.yml
lightautoml_gpu/automl/presets/gpu/tabular_gpu_config.yml
lightautoml_gpu/automl/presets/gpu/tabular_gpu_presets.py
lightautoml_gpu/automl/presets/gpu/text_gpu_config.yml
lightautoml_gpu/automl/presets/gpu/text_gpu_presets.py
lightautoml_gpu/automl/presets/image_config.yml
lightautoml_gpu/automl/presets/image_presets.py
lightautoml_gpu/automl/presets/tabular_config.yml
lightautoml_gpu-0.2.15.dist-info/LICENSE
lightautoml_gpu-0.2.15.dist-info/WHEEL
lightautoml_gpu-0.2.15.dist-info/METADATA
lightautoml_gpu-0.2.15.dist-info/RECORD
