Metadata-Version: 2.1
Name: lightautoml-gpu
Version: 0.2.15
Summary: Fast and customizable framework for automatic ML model creation (AutoML)
Home-page: https://lightautoml.readthedocs.io/en/latest/
License: Apache-2.0
Author: Alexander Ryzhkov
Author-email: AMRyzhkov@sberbank.ru
Requires-Python: >=3.6.1,<4.0.0
Classifier: Development Status :: 3 - Alpha
Classifier: Environment :: Console
Classifier: Intended Audience :: Science/Research
Classifier: License :: OSI Approved :: Apache Software License
Classifier: Natural Language :: Russian
Classifier: Operating System :: OS Independent
Classifier: Programming Language :: Python :: 3
Classifier: Programming Language :: Python :: 3.10
Classifier: Programming Language :: Python :: 3.6
Classifier: Programming Language :: Python :: 3.7
Classifier: Programming Language :: Python :: 3.8
Classifier: Programming Language :: Python :: 3.9
Classifier: Topic :: Scientific/Engineering :: Artificial Intelligence
Classifier: Typing :: Typed
Provides-Extra: pdf
Requires-Dist: albumentations (>=0.4.6)
Requires-Dist: autowoe (>=1.2)
Requires-Dist: cffi (>=1.14.5,<2.0.0); extra == "pdf"
Requires-Dist: cmaes
Requires-Dist: efficientnet-pytorch
Requires-Dist: gensim
Requires-Dist: holidays
Requires-Dist: importlib-metadata (>=1.0,<2.0); python_version < "3.8"
Requires-Dist: jinja2
Requires-Dist: joblib
Requires-Dist: json2html
Requires-Dist: lightgbm (>=2.3,<3.0)
Requires-Dist: log-calls
Requires-Dist: networkx
Requires-Dist: nltk
Requires-Dist: numpy
Requires-Dist: opencv-python
Requires-Dist: optuna
Requires-Dist: pandas (>=1)
Requires-Dist: poetry-core (>=1.0.0,<2.0.0)
Requires-Dist: pywavelets
Requires-Dist: pyyaml
Requires-Dist: scikit-image
Requires-Dist: scikit-learn (>=0.22)
Requires-Dist: scipy
Requires-Dist: seaborn
Requires-Dist: torch (>=1.6)
Requires-Dist: torchvision
Requires-Dist: tqdm
Requires-Dist: transformers (>=4)
Requires-Dist: weasyprint (>=52.5,<53.0); extra == "pdf"
Requires-Dist: webencodings
Project-URL: Repository, https://github.com/sberbank-ai-lab/LightAutoML
